ridt/__init__.py
ridt/analysis/__init__.py
ridt/analysis/batchdatastoreanalyser.py
ridt/analysis/batchresultswriter.py
ridt/analysis/datastoreanalyser.py
ridt/analysis/exposure.py
ridt/analysis/resultcontainers.py
ridt/analysis/resultswriter.py
ridt/base/__init__.py
ridt/base/exceptions.py
ridt/base/settings.py
ridt/cli/__init__.py
ridt/cli/ridt.py
ridt/config/__init__.py
ridt/config/configfileparser.py
ridt/config/configfilewriter.py
ridt/config/csvtoconfigfile.py
ridt/config/ridtconfig.py
ridt/config/summary.py
ridt/config/units.py
ridt/container/__init__.py
ridt/container/domain.py
ridt/container/eddydiffusionrun.py
ridt/container/wellmixedrun.py
ridt/data/__init__.py
ridt/data/batchdatastore.py
ridt/data/batchdatastoreplotter.py
ridt/data/batchdatastorewriter.py
ridt/data/datastore.py
ridt/data/datastorecsvwriter.py
ridt/data/datastoreplotter.py
ridt/data/datastorereader.py
ridt/data/datastorewriter.py
ridt/data/directoryagent.py
ridt/data/uncertaintymask.py
ridt/default/__init__.py
ridt/default/config.json
ridt/default/config.jsonc
ridt/equation/__init__.py
ridt/equation/eddy_diffusion.py
ridt/equation/well_mixed.py
ridt/plot/__init__.py
ridt/plot/contourplot.py
ridt/plot/lineplot.py
ridt/plot/pointplot.py
ridt/tests/__init__.py
ridt/tests/systemtests/__init__.py
ridt/tests/systemtests/test_st01.py
ridt/tests/systemtests/test_st02.py
ridt/tests/systemtests/test_st03.py
ridt/tests/systemtests/test_st04.py
ridt/tests/systemtests/test_st05.py
ridt/tests/systemtests/test_st06.py
ridt/tests/systemtests/test_st07.py
ridt/tests/systemtests/test_st08.py
ridt/tests/systemtests/test_st09.py
ridt/tests/systemtests/test_st10.py
ridt/tests/systemtests/test_st11.py
ridt/tests/systemtests/test_st12.py
ridt/tests/systemtests/test_st13.py
ridt/tests/systemtests/test_st14.py
ridt/tests/systemtests/test_st15.py
ridt/tests/systemtests/test_st16.py
ridt/tests/systemtests/test_st17.py
ridt/tests/systemtests/test_st18.py
ridt/tests/systemtests/test_st19.py
ridt-1.1.8.dist-info/LICENCE
ridt-1.1.8.dist-info/METADATA
ridt-1.1.8.dist-info/WHEEL
ridt-1.1.8.dist-info/entry_points.txt
ridt-1.1.8.dist-info/top_level.txt
ridt-1.1.8.dist-info/RECORD
