Metadata-Version: 2.1
Name: ridt
Version: 1.1.8
Summary: Rapid Indoor Diffusion Tool
Home-page: https://github.com/riskaware-ltd/ridt
Author: Riskaware Ltd
License: UNKNOWN
Platform: UNKNOWN
Classifier: Programming Language :: Python :: 3
Classifier: License :: OSI Approved :: MIT License
Classifier: Operating System :: OS Independent
Requires-Dist: click
Requires-Dist: scipy
Requires-Dist: matplotlib
Requires-Dist: tqdm
Requires-Dist: numpy (==1.16.5) ; python_version < "3.8"
Requires-Dist: numpy (==1.19.3) ; python_version >= "3.8"
